grapl_graph_descriptions_py/__init__.py
grapl_graph_descriptions_py/asset.py
grapl_graph_descriptions_py/dynamic_node.py
grapl_graph_descriptions_py/file.py
grapl_graph_descriptions_py/generated_graph.py
grapl_graph_descriptions_py/graph.py
grapl_graph_descriptions_py/graph_description_pb2.py
grapl_graph_descriptions_py/ip_address.py
grapl_graph_descriptions_py/ip_port.py
grapl_graph_descriptions_py/network_connection.py
grapl_graph_descriptions_py/process.py
grapl_graph_descriptions_py/process_inbound_connection.py
grapl_graph_descriptions_py/process_outbound_connection.py
grapl_graph_descriptions_py-0.3.1.dist-info/DESCRIPTION.rst
grapl_graph_descriptions_py-0.3.1.dist-info/METADATA
grapl_graph_descriptions_py-0.3.1.dist-info/RECORD
grapl_graph_descriptions_py-0.3.1.dist-info/WHEEL
grapl_graph_descriptions_py-0.3.1.dist-info/metadata.json
grapl_graph_descriptions_py-0.3.1.dist-info/top_level.txt
